code_towel-1.0.4.dist-info/licenses/LICENSE
towel/__init__.py
towel/cli.py
towel/unification/__init__.py
towel/unification/assignment_analyzer.py
towel/unification/ast_normalizer.py
towel/unification/ast_pretty_printer.py
towel/unification/binding_detector.py
towel/unification/block_signature.py
towel/unification/builtins.py
towel/unification/exceptions.py
towel/unification/extractor.py
towel/unification/models.py
towel/unification/nominal_unifier.py
towel/unification/orphan_detector.py
towel/unification/pipeline.py
towel/unification/project_layout.py
towel/unification/refactor_engine.py
towel/unification/scope_analyzer.py
towel/unification/unifier.py
towel/unification/visitor_utils.py
towel/unification/visitors.py
code_towel-1.0.4.dist-info/METADATA
code_towel-1.0.4.dist-info/WHEEL
code_towel-1.0.4.dist-info/entry_points.txt
code_towel-1.0.4.dist-info/top_level.txt
code_towel-1.0.4.dist-info/RECORD
